app/__init__.py
app/__main__.py
app/__version__.py
app/cli.py
app/config.py
app/constants.py
app/pomodoro.py
app/progress.py
app/proxy.py
app/sounds/__init__.py
app/sounds/ding.wav
doro-1.0.0.dist-info/METADATA
doro-1.0.0.dist-info/WHEEL
doro-1.0.0.dist-info/entry_points.txt
doro-1.0.0.dist-info/licenses/LICENSE
doro-1.0.0.dist-info/RECORD
