Metadata-Version: 2.4
Name: doro
Version: 1.0.0
Summary: CLI based pomodoro app
Author-email: Suresh Kumar <sureshdsk91@gmail.com>
License-File: LICENSE
Requires-Python: >=3.12.8
Requires-Dist: mitmproxy>=11.1.3
Requires-Dist: pyglet==1.5.19
Requires-Dist: pyyaml==6.0.2
Requires-Dist: rich==13.9.4
Requires-Dist: typer==0.15.2
